airctest/__init__.py
airctest/main.py
airctest/cli/__init__.py
airctest/cli/main.py
airctest-1.8.1.dist-info/licenses/LICENSE
configs/datasets.yaml
utils/util.py
airctest-1.8.1.dist-info/METADATA
airctest-1.8.1.dist-info/WHEEL
airctest-1.8.1.dist-info/entry_points.txt
airctest-1.8.1.dist-info/top_level.txt
airctest-1.8.1.dist-info/RECORD
