Metadata-Version: 2.4
Name: airctest
Version: 1.8.1
Summary: This repository contains the implementation of  dataset loader for Parquet files.
Author-email: Nabin Bagale <bhklab.nabinbagale@gmail.com>
Project-URL: Website, https://www.aircheck.ai/
Project-URL: Source Code, https://github.com/StructuralGenomicsConsortium/AIRCHECK-data-package
Project-URL: Bug Tracker, https://github.com/StructuralGenomicsConsortium/AIRCHECK-data-package/issues
Project-URL: Documentation, https://github.com/StructuralGenomicsConsortium/AIRCHECK-data-package
Classifier: Programming Language :: Python :: 3
Classifier: License :: OSI Approved :: MIT License
Classifier: Operating System :: OS Independent
Requires-Python: >=3.9
License-File: LICENSE
Requires-Dist: pandas>=1.3.0
Requires-Dist: pyarrow>=5.0.0
Requires-Dist: tqdm>=4.62.0
Requires-Dist: requests>=2.25.0
Requires-Dist: PyYAML>=5.4.0
Requires-Dist: gcsfs>=2025.3.2
Requires-Dist: click>=8.0.0
Provides-Extra: gcs
Requires-Dist: google-cloud-storage>=2.0.0; extra == "gcs"
Provides-Extra: dev
Requires-Dist: pytest>=7.0.0; extra == "dev"
Dynamic: license-file
